backoff-stubs/__init__.pyi
backoff_stubs-1.11.1.post1.dist-info/LICENSE
backoff_stubs-1.11.1.post1.dist-info/METADATA
backoff_stubs-1.11.1.post1.dist-info/WHEEL
backoff_stubs-1.11.1.post1.dist-info/top_level.txt
backoff_stubs-1.11.1.post1.dist-info/RECORD
